historicaldates/__init__.py
historicaldates/historical_date.py
historicaldates/test_historical_date.py
historicaldates-1.0.1.dist-info/LICENSE
historicaldates-1.0.1.dist-info/METADATA
historicaldates-1.0.1.dist-info/WHEEL
historicaldates-1.0.1.dist-info/top_level.txt
historicaldates-1.0.1.dist-info/RECORD
