Metadata-Version: 2.1
Name: historicaldates
Version: 1.0.1
Summary: Python library for handling BCE and CE dates.
Home-page: https://github.com/BrentLageson/python-historical-dates
Author: Brent Lageson
Author-email: brent.lageson@gmail.com
Classifier: Development Status :: 5 - Production/Stable
Classifier: Intended Audience :: Developers
Classifier: Natural Language :: English
Classifier: License :: OSI Approved :: MIT License
Classifier: Programming Language :: Python :: 3
Classifier: Programming Language :: Python :: 3.8
Classifier: Programming Language :: Python :: 3.9
Classifier: Operating System :: OS Independent
Requires-Python: >=3.6
License-File: LICENSE
